more_kivy_app/__init__.py
more_kivy_app/app.py
more_kivy_app/config.py
more_kivy_app/utils.py
more_kivy_app/tests/__init__.py
more_kivy_app/tests/test_app.py
more_kivy_app-0.1.2.dist-info/licenses/LICENSE
more_kivy_app-0.1.2.dist-info/METADATA
more_kivy_app-0.1.2.dist-info/WHEEL
more_kivy_app-0.1.2.dist-info/top_level.txt
more_kivy_app-0.1.2.dist-info/RECORD
