Metadata-Version: 2.4
Name: more_kivy_app
Version: 0.1.2
Summary: Base class for kivy apps that is crash resistant with builtin configuration.
Home-page: https://github.com/matham/more-kivy-app
Author: Matthew Einhorn
Author-email: moiein2000@gmail.com
License: MIT
Project-URL: Bug Reports, https://github.com/matham/more-kivy-app/issues
Project-URL: Source, https://github.com/matham/more-kivy-app
Classifier: Development Status :: 4 - Beta
Classifier: License :: OSI Approved :: MIT License
Classifier: Programming Language :: Python :: 3.7
Classifier: Programming Language :: Python :: 3.8
License-File: LICENSE
Requires-Dist: tree-config
Requires-Dist: kivy
Provides-Extra: dev
Requires-Dist: pytest>=3.6; extra == "dev"
Requires-Dist: pytest-cov; extra == "dev"
Requires-Dist: sphinx-rtd-theme; extra == "dev"
Requires-Dist: coveralls; extra == "dev"
Requires-Dist: sphinx; extra == "dev"
Requires-Dist: flake8; extra == "dev"
Requires-Dist: wheel; extra == "dev"
Dynamic: author
Dynamic: author-email
Dynamic: classifier
Dynamic: description
Dynamic: home-page
Dynamic: license
Dynamic: license-file
Dynamic: project-url
Dynamic: summary
